core_app/__init__.py
core_app/admin.py
core_app/apps.py
core_app/models.py
core_app/tests.py
core_app/views.py
core_app/migrations/__init__.py
profile_api/__init__.py
profile_api/admin.py
profile_api/apps.py
profile_api/models.py
profile_api/serializers.py
profile_api/signals.py
profile_api/tests.py
profile_api/views.py
profile_api/migrations/0001_initial.py
profile_api/migrations/__init__.py
user/__init__.py
user/asgi.py
user/urls.py
user/wsgi.py
user/settings/__init__.py
user/settings/base.py
user/settings/dev.py
user/settings/prod.py
user/settings/uat.py
user_api/__init__.py
user_api/admin.py
user_api/apps.py
user_api/managers.py
user_api/models.py
user_api/serializers.py
user_api/urls.py
user_api/views.py
user_api/migrations/0001_initial.py
user_api/migrations/0002_auto_20201226_0712.py
user_api/migrations/__init__.py
user_api/tests/__init__.py
user_api/tests/test_token_create.py
user_api/tests/test_token_destroy.py
user_api/tests/test_user_create.py
user_api/tests/test_user_delete.py
user_api/tests/test_user_detail.py
user_api/tests/test_user_list.py
user_api/tests/test_user_me.py
user_api/tests/utils_ts.py
crouber_user_api-0.1.dist-info/LICENSE
crouber_user_api-0.1.dist-info/METADATA
crouber_user_api-0.1.dist-info/WHEEL
crouber_user_api-0.1.dist-info/top_level.txt
crouber_user_api-0.1.dist-info/RECORD
