Metadata-Version: 2.1
Name: crouber-user-api
Version: 0.1
Summary: A Django API app with 'user' features which can serve other projects.
Home-page: https://www.crouber.com/
Author: Yanick A. Anagho
Author-email: yanickanagho@gmail.com
License: BSD 3-Clause License
Platform: UNKNOWN
Classifier: Environment :: Web Environment
Classifier: Framework :: Django
Classifier: Framework :: Django :: 3.1
Classifier: Intended Audience :: Developers
Classifier: License :: OSI Approved :: BSD License
Classifier: Operating System :: OS Independent
Classifier: Programming Language :: Python
Classifier: Programming Language :: Python :: 3
Classifier: Programming Language :: Python :: 3 :: Only
Classifier: Programming Language :: Python :: 3.6
Classifier: Programming Language :: Python :: 3.7
Classifier: Programming Language :: Python :: 3.8
Classifier: Topic :: Internet :: WWW/HTTP
Classifier: Topic :: Internet :: WWW/HTTP :: Dynamic Content
Requires-Dist: django-phonenumber-field[phonenumberslite]
Requires-Dist: djoser
